{
    "advert": {
        "campaign": {
            "placeholders": {
                "link": "Link għall-promozzjoni",
                "startDate": "Data tal-Bidu",
                "startTime": "Ħin tal-Bidu",
                "endDate": "Data tat-Tmiem",
                "endTime": "Ħin tat-Tmiem",
                "budget": "Baġit"
            },
            "interests": {
                "Title": "Iffiltra mill-Interess",
                "FilterInterests": "Ibda ttajpja interess..."
            },
            "Interest": "Interess",
            "Location": "Post"
        }
    },
    "webpage": {
        "composer": {
            "Go": "Mur",
            "PasteLinkHere": "https:\/\/...",
            "BrowseTheWeb": "Fittex",
            "WriteToStartConversation": "Ikteb il-ħsibijiet tiegħek biex tibda l-konversazzjoni",
            "StartConversation": "Ibda Konversazzjoni",
            "GotoConversation": "Mur fil-Konversazzjoni",
            "reset": "Irrisettja",
            "edit": "Editja",
            "link": "Link",
            "setUrl": "Issettja l-URL",
            "save": "Ħlief",
            "setClip": "Aqta&#39; Clip",
            "invalidURL": "URL invalidu"
        },
        "FileTooLarge": "Fajl kbir wisq għall-caching. Daqs massimu tal-fajl {{size}}",
        "InvalidPDF": "Il-fajl mhuwiex PDF validu",
        "StartTypingTitleOrKeywords": "Ibda ttajpja t-titlu jew il-kliem kjavi..."
    },
    "types": {
        "Websites\/article": {
            "description": "Dokument HTML li diversi utenti jistgħu jaraw u jeditjaw",
            "displayType": "Artikolu"
        },
        "Websites\/slide": {
            "description": "Slide fi preżentazzjoni, tista &#39;tinkludi HTML, awdjo eċċ.",
            "displayType": "Slide"
        },
        "Websites\/presentation": {
            "description": "Preżentazzjoni li tikkonsisti minn diversi slides",
            "displayType": "Preżentazzjoni"
        },
        "Websites\/advert\/unit": {
            "description": "Unità ta&#39; reklamar fuq websajt",
            "displayType": "Unità reklam"
        },
        "Websites\/advert\/placement": {
            "description": "Mod ta &#39;raggruppament ta&#39; unitajiet ta &#39;reklamar taħt isem",
            "displayType": "Tqegħid tar-reklam"
        },
        "Websites\/advert\/creative": {
            "description": "Kontenut għal reklam",
            "displayType": "Irreklama kreattiv"
        },
        "Websites\/advert\/campaign": {
            "description": "Kampanja ta’ reklamar",
            "displayType": "Kampanja reklam"
        },
        "Websites\/webpage": {
            "description": "Jirrappreżenta websajt li l-metadata tagħha ġiet mibruxa",
            "displayType": "Paġna tal-web"
        }
    }
}