{
    "errors": {
        "Error": "Errorea",
        "WalletAbsent": "Diru-zorroa ez dago konektatuta.",
        "Rendering": "Erroreak egon dira <span class='url'>{{1}}<\/span> errendatzean",
        "PriceRequired": "Prezioa beharrezkoa!",
        "NameRequired": "Izena behar da!",
        "PriceInvalid": "Prezioa baliogabea!",
        "AmountInvalid": "Zenbatekoa baliogabea!",
        "TransactionFailed": "Transakzioak huts egin du",
        "ChainNotSupported": "Hautatutako katea ez da onartzen. Onartutako katea: {{supportedChain}}",
        "NeedMetaMaskConnected": "MetaMask konektatuta behar da aplikazioarekin lan egiteko",
        "UserNotLoggedInMetaMask": "Erabiltzailea ez dago MetaMask-en saioa hasita",
        "CurrencyNotFound": "Ez da moneta aurkitu",
        "WrongChain": "NFT hau &quot; {{chain}} &quot; pean sortu da. Mesedez, erabili kate hau.",
        "NoRecipientSelected": "Ez da hartzailerik hautatu",
        "NotEnoughPermissionsWallet": "Ez dago nahikoa baimen erabiltzailearen zorroa irakurtzeko",
        "ThisUserHaveNoWallet": "Erabiltzaile honek ez du diru-zorrorik esleitu",
        "TheWalletOfThisUserInvalid": "Erabiltzaile honen zorroa baliogabea",
        "WalletInvalid": "Diru-zorroaren helbidea baliogabea"
    },
    "admin": {
        "Title": "Ondasunen administrazioa",
        "SubscriptionTitle": "Harpidetza planak"
    },
    "browsertab": {
        "html": "{{button}}",
        "button": "Sakatu ordaintzeko"
    },
    "notifications": {
        "ChargeProcessedFor": "{{call 'publisher.displayName'}} : {{call 'user.displayName'}} karga prozesatu da",
        "ThankYouForYourPayment": "Eskerrik asko {{call 'publisher.displayName'}} ordaintzeagatik",
        "SubscribedTo": "{{call 'user.displayName'}} {{plan.title}} harpidetu ziren",
        "YouSubscribedTo": "{{plan.title}} harpidetuta zaude",
        "Assets\/credits\/alert": "Zure kontuarekin lotutako alerta duzu"
    },
    "charge": {
        "Subject": "{{displayAmount}} ordaintzen dituzu {{call 'publisher.displayName'}} &quot; {{description}} &quot; bidez",
        "HasBeenCharged": "Aizu, hau {{1}} {{2}} kobratu zaizkiola {{3}} {{4}} jakinarazteko besterik ez da"
    },
    "charged": {
        "Subject": "Eskerrik asko &quot; {{description}} &quot;-ren ordainketagatik",
        "HavePaid": "Kaixo {{1}} , hau {{2}} {{3}} {{4}} 1000tik 1001ra behar bezala ordaindu duzulako baieztapen azkar bat besterik ez da"
    },
    "payment": {
        "AboutOrder": "Eskaerari buruzko informazioa",
        "PaymentMethod": "Ordainketa modua",
        "ContactInfo": "Harremanetarako informazioa",
        "Pay": "Ordaindu",
        "PaymentSucceeded": "Ordainketa arrakastatsua izan da",
        "PaymentProcessing.": "Ordainketa prozesatzen ari da",
        "FailTryAgain": "Ordainketa ez da arrakasta izan. Saiatu berriro",
        "SomethingWrong": "Zerbait gaizki joan da",
        "PaymentStatus": "Ordainketa egoera",
        "PayTo": "Ordaindu {{displayName}}",
        "ChooseCurrency": "Aukeratu moneta bat",
        "YouCanSendUpTo": "Gehienez {{amount}} {{symbol}} bidal ditzakezu",
        "Send": "Bidali",
        "EnterAmount": "sartu zenbatekoa"
    },
    "credits": {
        "InviteAcceptedBy": "{{invitedUserName}} gonbidapena onartu du",
        "InvitedUserFilledStream": "{{invitedUserName}} bete {{FilledStreamTitle}}",
        "ForFillingStream": "{{FilledStreamTitle}} betetzeko",
        "YouHaveCreditsToStart": "{{amount}} kreditu dituzu hasteko",
        "PaymentFor": "&quot; {{1}} &quot;-ren ordainketa",
        "PaymentTo": "Ordainketa {{1}}",
        "PaymentToUser": "Ordainketa {{toUserName}}",
        "CreatePrivateChat": "{{toUserName}} rekin txateatzeko",
        "CreatePaidStream": "{{toStreamName}} sortzeko",
        "JoinedPaidStream": "erreserba egiteko &quot; <a data-publisherId='<i translate='no'>999 &#39; data-streamName=&#39; {{toStreamName}} &#39;&gt; {{toStreamTitle}}<\/a> &quot;",
        "CreatedCommunity": "komunitatea sortzeko &quot; {{communityId}} &quot;",
        "LeftPaidStream": "erreserbaren itzulketa gisa &quot; <a data-publisherId='<i translate='no'>999 &#39; data-streamName=&#39; {{fromStreamName}} &#39;&gt; {{fromStreamTitle}}<\/a> &quot; atalean",
        "BoughtCredits": "{{amount}} kreditu erosi ditu",
        "BonusCredits": "{{amount}} kreditu gehigarria",
        "BuyAmountCredits": "Erosi {{amount}} kreditu",
        "WatchClip": "{{amount}} kreditu lortu ditu {{fromStreamTitle}} ikusteagatik",
        "MissingCredits": "Kredituak falta dira",
        "YouMissingCredits": "{{amount}} kreditu gehiago behar dituzu aurrera egiteko.",
        "BuyCredits": "Erosi kredituak",
        "BuyBonus": "{{amount}} kreditu aldi berean erostea, {{bonus}} kreditu hobaria ekarriko du.",
        "Buy": "Erosi",
        "PurchaseCredits": "Erosketa Kredituak",
        "Credits": "Kredituak",
        "ErrorInvalidAmount": "Zenbatekoa baliogabea",
        "ErrorInvalidCurrency": "Zoritxarrez, oraindik ez dugu {{currency}} moneta onartzen",
        "forMessages": {
            "BoughtCredits": "{{amount}} kreditu",
            "BonusCredits": "{{amount}} kreditu"
        }
    },
    "history": {
        "Date": "Data",
        "Amount": "Zenbatekoa",
        "Description": "Deskribapena",
        "Client": "Bezeroa",
        "User": "Erabiltzailea",
        "To": "to",
        "From": "tik",
        "SeeHistory": "Ikusi {{1}} ordainketen historia",
        "HistoryEmpty": "Oraindik ez duzu daturik",
        "PaymentFor": "{{amount}} kreditu bidali ditu",
        "PaymentTo": "{{amount}} kreditu bidali ditu",
        "PaymentToUser": "{{amount}} kreditu bidali ditu",
        "CreatePaidStream": "{{amount}} kreditu gastatu",
        "WatchClip": {
            "+": "{{amount}} kreditu lortu ditu",
            "-": "{{amount}} kreditu gastatu"
        },
        "JoinedPaidStream": {
            "+": "{{amount}} kreditu lortu ditu",
            "-": "{{amount}} kreditu gastatu"
        },
        "LeftPaidStream": {
            "+": "{{amount}} kreditu jaso ditu",
            "-": "{{amount}} kreditu bidali ditu"
        },
        "CreatedCommunity": "{{amount}} kreditu gastatu",
        "BoughtCredits": "{{amount}} kreditu erosi ditu",
        "BonusCredits": "{{amount}} kreditu bonus lortu ditu",
        "InviteAcceptedBy": "{{amount}} kreditu lortu ditu",
        "Streams_user_firstname": "{{amount}} kreditu lortu ditu",
        "Streams_user_lastname": "{{amount}} kreditu lortu ditu",
        "Streams_user_icon": "{{amount}} kreditu lortu ditu",
        "Places_user_location": "{{amount}} kreditu lortu ditu",
        "Streams_greeting": "{{amount}} kreditu lortu ditu",
        "YouHaveCreditsToStart": "{{amount}} kreditu lortu ditu"
    },
    "subscriptions": {
        "infoTitle": "Ezarri ordainketa-informazioa",
        "confirm": {
            "title": "Hasi Harpidetza",
            "message": "&quot; {{title}} &quot;-rako harpidetza errepikakorra hasi?",
            "ok": "Ados",
            "cancel": "Utzi"
        },
        "CreditOrDebitCard": "Kreditu edo zordunketa txartela",
        "SubscribePayment": "Harpidetza Ordainketa",
        "ImmediatePayment": "Berehalako Ordainketa",
        "ProcessingPayment": "Ordainketa tramitatzea",
        "SubscriptionAlreadyPaid": "Harpidetza hau jada ordainduta dago",
        "SubscriptionNotActive": "Harpidetza hau ez dago aktibo",
        "Subscribed": "Harpidetuta",
        "Unsubscribed": "Harpidetza kendu da",
        "Unsubscribe": "Harpidetza kendu",
        "Subscribe": "Harpidetu",
        "Started": "Hasi da",
        "EndsIn": "urtean amaitzen da",
        "NextPay": "Hurrengo ordainketa",
        "Period": "Aldia",
        "Price": "Prezioa",
        "AreYouSureUnsubscribe": "Ziur plan honen harpidetza kendu nahi duzula?",
        "YouUnsubscribedFromPlan": "&quot; {{planTitle}} &quot; planaren harpidetza kendu duzu. Ez duzu kobratuko, baina harpidetzak {{endsIn}} arte jarraituko du",
        "plan": {
            "TitlePlaceholder": "planaren izenburua",
            "PricePlaceholder": "prezioa",
            "DescriptionPlaceholder": "harpidetza planaren deskribapena",
            "SavePlan": "Gorde plana",
            "NewPlan": "Plan Berria"
        }
    },
    "payments": {
        "infoTitle": "Ezarri ordainketa-informazioa",
        "BuyAmountCredits": "Erosi {{amount}} kreditu",
        "confirm": {
            "title": "Egin Ordainketa",
            "message": "Ados zaude {{symbol}} {{amount}} ordaintzea?",
            "ok": "Ados",
            "cancel": "Utzi"
        }
    },
    "types": {
        "Assets\/credits": {
            "displayType": "Kredituak",
            "description": "kredituen eta ordainketen jarraipena egiten du"
        },
        "Assets\/plan": {
            "displayType": "Harpidetza Plana",
            "description": "harpidetza plana"
        },
        "Assets\/subscription": {
            "displayType": "Harpidetza",
            "description": "harpidetza"
        },
        "Assets\/product": {
            "displayType": "Produktua",
            "description": "saltzen ari den produktua"
        },
        "Assets\/service": {
            "displayType": "Zerbitzua",
            "description": "eskaintzen ari den zerbitzua"
        }
    },
    "messages": {
        "Assets\/credits\/earned": {
            "content": "{{amount}} kreditu lortu ditu"
        },
        "Assets\/credits\/bought": {
            "content": "{{amount}} kreditu erosi ditu"
        },
        "Assets\/credits\/bonus": {
            "content": "{{amount}} kreditu gehigarria"
        },
        "Assets\/credits\/spent": {
            "content": "{{amount}} kreditu gastatu"
        },
        "Assets\/credits\/sent": {
            "content": "{{amount}} kreditu bidali ditu {{toUserName}}"
        },
        "Assets\/credits\/received": {
            "content": "{{fromUserName}} {{amount}} kreditu jaso ditu"
        },
        "Assets\/credits\/alert": {
            "content": "Kreditu gutxi dituzu zure kontuan. Mesedez, bisitatu <a href='<i translate='no'>999 &#39;&gt; esteka hau<\/a> kreditu gehiago erosteko."
        }
    },
    "billing": {
        "Title": "Aktiboen fakturazioa",
        "CreditsMinimum": "Gutxieneko kredituak",
        "CreditsToAdd": "Gehitzeko kredituak",
        "Save": "Gorde",
        "ThisLink": "esteka hau",
        "errors": {
            "CreditsMinimumNegative": "Gutxieneko kredituak ezin dira negatiboak izan",
            "CreditsToAddNegative": "Gehitzeko kredituak ezin dira negatiboak izan"
        }
    },
    "services": {
        "NewServiceTemplate": {
            "Title": "Zerbitzu berria",
            "TitlePlaceholder": "Zerbitzuaren titulua",
            "PricePlaceholder": "Ezarri prezioa",
            "LinkPlaceholder": "ezarri informazio gehigarria esteka",
            "DescriptionPlaceholder": "Zerbitzuaren deskribapena",
            "SaveService": "Gorde Zerbitzua",
            "SelectRequiredParticipants": "Beharrezko erlazionatutako parte-hartzaileak",
            "RequiredParticipantsDesc": "Mesedez, hautatu zerbitzu hau erabiltzeko beharrezkoak diren erlazionatutako parte-hartzaileak (adibidez, maskotak &quot;Txakurren erakustaldirako&quot;, edo haurrak &quot;Haurren oporretarako&quot;, etab). Zerbitzua ordaintzen bada, erabiltzaileak erlazionatutako parte-hartzaile bakoitzeko ere ordaindu beharko du."
        },
        "EditServiceTemplate": {
            "Title": "Editatu Zerbitzua"
        },
        "ManageServiceTemplates": "Kudeatu Zerbitzu Txantiloiak",
        "ManageServices": "Kudeatu Zerbitzuak",
        "Free": "Doan",
        "OptionalContribution": "Aukerako ekarpena",
        "RequiredPayment": "Beharrezko ordainketa",
        "AreYouSureDelete": "Ziur zerbitzu hau ezabatu nahi duzula?",
        "AmountServicesRelated": "Zerbitzu honekin lotutako {{amount}} erabilgarritasun daude. Horiek ere kenduko dira."
    },
    "transfer": {
        "SelectRecipient": "Hautatu hartzailea",
        "TransactionSuccess": "Transakzio arrakastatsua",
        "OrTypeWalletAddress": "EDO idatzi hartzailearen zorroaren helbidea"
    },
    "NFT": {
        "Title": "Izenburua",
        "Name": "Izena",
        "EnterName": "Sartu izena",
        "EnterAuthorWallet": "Sartu egilearen zorroa",
        "InformationAboutTitle": "{{title}} NFTri buruzko informazioa",
        "Description": "Deskribapena",
        "DetailedInformationAboutNFT": "NFTri buruzko informazio zehatza",
        "PresaleStarts": "Aurresalmenta abenduaren 23an hasiko da",
        "OwnerUserNotFound": "NFT honen jabea ez dago gure aplikazioan erregistratuta.",
        "BuyNow": "Erosi orain",
        "Buy": "Erosi",
        "Add": "Gehitu",
        "Remove": "Kendu",
        "NoNFTyet": "Oraindik ez dago NFTrik",
        "Conversation": "Elkarrizketa",
        "Create": "Sortu",
        "CurrentBid": "Oraingo eskaintza",
        "StartingIn": "urtean hasita",
        "EndingIn": "Amaitzen",
        "CreateNFT": "Sortu NFT bat",
        "TitlePlaceholder": "Eman izenburu bat zure NFTri",
        "DescriptionPlaceholder": "Eman zure NFT deskribapen bat",
        "CreateYourNFT": "Sortu zure NFT",
        "Royalties": "Royalties",
        "RoyaltyPlaceholder": "Aukerakoa. Sortzaileari transferitu aurretik ordaindutako zenbatekoa.",
        "ExpirationDate": "Iraungitze-data",
        "StartingDate": "Hasiera data",
        "BidsBelowThisAmount": "Kopuru horretatik beherako eskaintzak ez dira onartuko",
        "MinimumBid": "Gutxieneko eskaintza",
        "Author": "Egilea",
        "Price": "Prezioa",
        "Commission": "Batzordea",
        "EnterCommission": "Sartu komisioa",
        "Owner": "Jabea",
        "SelectCategory": "Hautatu kategoria",
        "Day": "Eguna",
        "Days": "Egunak",
        "Hour": "Ordua",
        "Hours": "Orduak",
        "Minute": "Minutua",
        "Minutes": "Minutu",
        "Second": "Bigarrena",
        "Seconds": "Segundoak",
        "SalesCreator": "salmenten kopurua sortzailearentzat izango da",
        "Details": "Xehetasunak",
        "Bids": "Eskaintzak",
        "History": "Historia",
        "LoremIpsum": "Lorem Ipsum inprimaketa eta konposaketa industriaren testu finko bat besterik ez da.",
        "PutOnSale": "Salgai jarri",
        "PutOffSale": "Salmentatik kendu",
        "Transfer": "Transferentzia",
        "Actions": "Ekintzak",
        "Claim": "Erreklamazioa",
        "ClaimNFT": "Erreklamatu NFT",
        "Unlocking": "Desblokeatzea",
        "Unlock": "Desblokeatu",
        "Update": "Eguneratu",
        "UpdateToken": "Eguneratu tokena",
        "UpdateNFT": "Eguneratu NFT",
        "CreateToken": "Sortu tokena",
        "PlaceBid": "Jarri eskaintza",
        "SoldOut": "Saldu",
        "NotOnSale": "Ez Salgai",
        "NftName": "NFT izena",
        "DescribeYourNFT": "Mesedez, deskribatu zure NFT",
        "NftPicture": "NFT irudikatzeko irudia",
        "NftMovie": "NFT irudikatzeko filma",
        "UploadMovie": "Kargatu filma",
        "MovieSource": "Filmaren iturria",
        "MovieURL": "Filmaren URLa",
        "UploadFile": "Kargatu fitxategi bat",
        "PutOnMarketplace": "Jarri merkatuan",
        "InstantPurchase": "Sartu prezioa erabiltzaileek zure NFT berehala erosteko",
        "FixedPrice": "Prezio finkoa",
        "TimedAuction": "Enkante garaia",
        "OpenForBids": "Eskaintzak zabalik",
        "PriceOnePiece": "Sartu pieza baten prezioa",
        "EnterPrice": "Sartu prezioa",
        "EnterMinimumBid": "Sartu Gutxieneko eskaintza",
        "SelectChain": "Hautatu katea",
        "Currency": "Moneta",
        "AreYouSureDeleteImage": "Ziur irudia kendu nahi duzula?",
        "AreYouSureDeleteVideo": "Ziur bideoa kendu nahi duzula?",
        "series": {
            "Name": "Izena",
            "Icon": "Ikonoa",
            "Description": "Deskribapena",
            "Author": "Egilea",
            "SelectSeries": "Hautatu seriea",
            "Value": "Balioa",
            "AreYouSure": "Ziur zaude?",
            "AuthorInvalid": "Egilearen helbidea baliogabea!",
            "Address": "Helbidea",
            "CoverImage": "Azaleko irudia",
            "UploadCoverImage": "Kargatu azaleko irudia",
            "CommissionAddressInvalid": "Batzordearen helbidea baliogabea",
            "OnSale": "salgai",
            "OffSale": "salmentatik kanpo",
            "CreateSeries": "Sortu Seriea",
            "UpdateSeries": "Eguneratu seriea",
            "SeriesInfo": "Serieari buruzko informazioa",
            "SelectAuthor": "Hautatu egilea",
            "NewItem": "NFT serie berria",
            "NamePlaceholder": "Sartu seriearen izena",
            "DescPlaceholder": "Sartu seriearen deskribapena",
            "EndingIn": "Amaitzen"
        },
        "contract": {
            "CreateContract": "Kontratua sortu",
            "SelectContract": "Aukeratu kontratua",
            "CreateContractFor": "Sortu {{userName}} kontratua",
            "ContractFor": "{{userName}} kontratua",
            "UpdateContract": "Kontratua eguneratzea",
            "TransferOwnership": "Jabetza transferitzea",
            "SetBaseURI": "Ezarri Oinarrizko URIa",
            "SetSuffix": "Ezarri atzizkia",
            "CurrentOwner": "Egungo jabea",
            "CurrentBaseURL": "Uneko BaseURL",
            "ContractAddressAbsent": "Kontratuaren helbidea falta da",
            "FactoryAddressAbsent": "Fabrikaren helbidea ez dago",
            "ContractName": "{{contractName}} - {{contractSymbol}} ( {{chainNetwork}} )",
            "TitleRequired": "Izenburua behar da",
            "SymbolRequired": "Sinboloa behar da",
            "TypeContractName": "kontratuaren izena",
            "TypeContractSymbol": "kontratuaren ikurra (gehienez 10 karaktere)"
        },
        "contests": {
            "Title": "Lehiaketak",
            "NewContest": "Lehiaketa Berria"
        },
        "import": {
            "importNFT": "NFT-ak inportatzea",
            "importAttributes": "Inportatu NFT atributuak",
            "fileNotFound": "Barkatu, ez da CSV fitxategia aurkitu.",
            "fileEmpty": "Barkatu, CSV fitxategia hutsik dago.",
            "userIdNotFound": "erabiltzailea existitzen da baina id hutsik",
            "errorLine": "{{1}} lerroa",
            "fieldNotFound": "Ez da &quot; {{1}} &quot; derrigorrezko eremua aurkitu",
            "displayTypeEmpty": "&quot; {{1}} &quot;-rako pantaila mota ez da aurkitu",
            "taskStreamInvalid": "ataza-korrontea baliogabea",
            "instructionsEmpty": "ataza-korrontearen argibideak hutsik",
            "complete": "Osatu",
            "activateUsers": "erabiltzaileei aktibazio-mezua bidali?",
            "importProgress": "Aurrerapena",
            "importOptions": "Aukerak",
            "sampleCSV": "Deskargatu Sample CSV",
            "fileLabel": "Kargatu kalkulu-orria:",
            "errorsTitle": "Erroreak gertatu dira"
        },
        "filter": {
            "ByCategory": {
                "FilterByNFTCollections": "Iragazi NFT Bildumen arabera",
                "ShowNFTCollection": "Erakutsi NFT bilduma...",
                "AllCollections": "Bilduma guztiak"
            },
            "ByUser": {
                "AllAuthors": "Egile guztiak",
                "AllUsers": "Denek",
                "FilterByAuthors": "Iragazi egileen arabera"
            }
        },
        "Back": "Bildumara itzuli",
        "attributes": {
            "Title": "Kudeatu Atributuak",
            "Attributes": "Atributuak",
            "DisplayTitle": "Bistaratzeko mota",
            "AddDisplayType": "Gehitu pantaila mota berria",
            "NewDisplay": "Pantaila berria",
            "TraitTitle": "Ezaugarri Mota",
            "AddTraitTitle": "Gehitu ezaugarri mota berria",
            "NewTrait": "Ezaugarri mota berria",
            "ValueTitle": "Balioa",
            "AddValueTitle": "Gehitu balio berria",
            "NewValue": "Balio Berria",
            "NewAttribute": "Atributu berria",
            "UpdateAttributes": "Eguneratu atributuak",
            "SaveAttributes": "Gorde atributuak"
        },
        "profile": {
            "LogOut": "Saioa amaitu",
            "Title": "{{userName}} ren profila",
            "Description": "Erabiltzailearen datuak",
            "aboutPlaceholder": "Editatu biografia",
            "SureLogOut": "Ziur saioa amaitu nahi duzula?"
        },
        "sales": {
            "factory": {
                "form": {
                    "labels": {
                        "NFTContract": "NFTKontratua",
                        "seriesId": "seriearen id",
                        "owner": "Jabea",
                        "currency": "Txanda",
                        "price": "Prezioa",
                        "beneficiary": "Onuraduna",
                        "autoindex": "Autoindex",
                        "duration": "Iraupena",
                        "rateInterval": "Tasa tartea",
                        "rateAmount": "Tasaren zenbatekoa"
                    },
                    "small": {
                        "NFTContract": "NFTKontratua",
                        "seriesId": "serie honetan tokenak sortuko dira",
                        "owner": "instantziaren jabea, bestela igorlea izango da",
                        "currency": "Erositako tokenen txanpona, zero bada, bertako txanponetarako",
                        "price": "Prezioa",
                        "beneficiary": "Tokenak saltzeko onuraduna, bestela igorlea izango da",
                        "autoindex": "Autoindex",
                        "duration": "Blokeatu egin ondoren. Zero esan nahi du berehala lortzea.",
                        "rateInterval": "erosketa berezirako kubo tartea",
                        "rateAmount": "erosketa berezirako kuboaren zenbatekoa"
                    }
                },
                "placeholders": {
                    "optional": "(aukerakoa)",
                    "number": "zenbakia",
                    "address": "helbidea",
                    "fraction": "zatikia",
                    "integer": "osokoa",
                    "seconds": "segundoak",
                    "uint256": "uint256",
                    "uint192": "uint192",
                    "uint64": "uint64",
                    "uint32": "uint32",
                    "uint16": "uint16"
                },
                "produce": "Ekoiztu",
                "viewInstancesList": "Freskatu zerrenda"
            },
            "instance": {
                "form": {
                    "labels": {
                        "seriesId": "Seriearen IDa",
                        "account": "Kontua",
                        "amount": "Zenbatekoa"
                    },
                    "small": {
                        "seriesId": "token berria seriean sartuko da ID horrekin",
                        "account": "sortu berri den NFTren jabea. ezartzen ez bada - uneko diru-zorroa erabiliko du",
                        "amount": "zenbatekoa NFT mint"
                    }
                },
                "placeholders": {
                    "optional": "(aukerakoa)",
                    "seriesId": "id",
                    "account": "kontua",
                    "amount": "zenbatekoa",
                    "integer": "osokoa"
                },
                "btn": {
                    "Purchase": "Erosketa",
                    "SpecialPurchase": "Erosketa berezia"
                }
            },
            "whitelist": {
                "form": {
                    "labels": {
                        "account": "Helbidea"
                    },
                    "small": {
                        "account": "Helbidea"
                    }
                },
                "errors": {
                    "invalidAddress": "Helbide baliogabea"
                },
                "placeholders": {
                    "account": "Helbidea"
                },
                "addToWhitelist": "Gehitu zerrenda zurira",
                "removeFromWhitelist": "Kendu zerrenda zuritik"
            }
        },
        "locked": {
            "form": {
                "labels": {
                    "tokenId": "Token IDa",
                    "custodian": "Zaintza",
                    "recipient": "Hartzailea"
                },
                "small": {
                    "tokenId": "token id zer blokeatu edo desblokeatu behar den",
                    "custodian": "desblokeatzeko gai izan daitekeen helbidea",
                    "recipient": "tokenak jasoko dituen helbidea"
                }
            },
            "errors": {
                "invalidTokenId": "TokenId baliogabea",
                "invalidCustodian": "Zaintza baliogabea",
                "invalidRecipient": "Hartzaile baliogabea"
            },
            "placeholders": {
                "optional": "(aukerakoa)",
                "tokenId": "id",
                "custodian": "helbidea"
            },
            "Lock": "Blokea",
            "Unlock": "Desblokeatu",
            "Locked": "Blokeatua",
            "CustodianAddress": "Zaindariaren helbidea",
            "TokenWasClaimed": "&quot; {{title}} &quot; tokena erreklamatu zen",
            "TokenWasLocked": "&quot; {{title}} &quot; tokena blokeatu zen",
            "TokenWasUnlocked": "&quot; {{title}} &quot; tokena desblokeatu zen"
        }
    },
    "currencies": {
        "choose": "Aukeratu moneta bat"
    }
}